etiq/spark.cpython-310-darwin.so
etiq/spark.pyi
etiq_spark-1.6.0.dist-info/METADATA
etiq_spark-1.6.0.dist-info/WHEEL
etiq_spark-1.6.0.dist-info/top_level.txt
etiq_spark-1.6.0.dist-info/RECORD
