Metadata-Version: 2.1
Name: etiq-spark
Version: 1.6.0
Summary: This is an optional, extension to the etiq library to provide spark datasets
Author-email: ETIQ AI <devops@etiq.ai>
Project-URL: homepage, https://etiq.ai
Keywords: ai,bias,etiq,fairness
Classifier: Development Status :: 5 - Production/Stable
Classifier: Environment :: Console
Classifier: Environment :: MacOS X
Classifier: Environment :: Win32 (MS Windows)
Classifier: Framework :: IPython
Classifier: Framework :: Jupyter
Classifier: Intended Audience :: Science/Research
Classifier: License :: Other/Proprietary License
Classifier: Natural Language :: English
Classifier: Programming Language :: Python :: 3.8
Classifier: Programming Language :: Python :: 3.9
Classifier: Programming Language :: Python :: 3.10
Classifier: Programming Language :: Python :: 3.11
Classifier: Programming Language :: Python :: 3.12
Classifier: Topic :: Scientific/Engineering
Classifier: Topic :: Scientific/Engineering :: Artificial Intelligence
Classifier: Topic :: Scientific/Engineering :: Information Analysis
Requires-Python: <3.13,>=3.8
Requires-Dist: etiq==1.6.0
Requires-Dist: pyspark[pandas_on_spark]>=3.3.2
